vimlm.py
vimlm-0.1.2.dist-info/LICENSE
vimlm-0.1.2.dist-info/METADATA
vimlm-0.1.2.dist-info/WHEEL
vimlm-0.1.2.dist-info/entry_points.txt
vimlm-0.1.2.dist-info/top_level.txt
vimlm-0.1.2.dist-info/RECORD
