Metadata-Version: 2.2
Name: vimlm
Version: 0.1.2
Summary: VimLM - LLM-powered Vim assistant
Home-page: https://github.com/JosefAlbers/vimlm
Author: Josef Albers
Author-email: albersj66@gmail.com
Requires-Python: >=3.12.8
License-File: LICENSE
Requires-Dist: nanollama>=0.0.6
Requires-Dist: mlx_lm_utils>=0.0.4
Requires-Dist: watchfiles==1.0.4
Dynamic: author
Dynamic: author-email
Dynamic: description
Dynamic: description-content-type
Dynamic: home-page
Dynamic: requires-dist
Dynamic: requires-python
Dynamic: summary
